README.md
setup.py
csg2csg/Card.py
csg2csg/CellCard.py
csg2csg/FLUKACellCard.py
csg2csg/FLUKAInput.py
csg2csg/FLUKAMaterialCard.py
csg2csg/FLUKASurfaceCard.py
csg2csg/Input.py
csg2csg/MCNPCellCard.py
csg2csg/MCNPDataCard.py
csg2csg/MCNPFormatter.py
csg2csg/MCNPInput.py
csg2csg/MCNPMaterialCard.py
csg2csg/MCNPParticleNames.py
csg2csg/MCNPSurfaceCard.py
csg2csg/MaterialCard.py
csg2csg/MaterialData.py
csg2csg/OpenMCCell.py
csg2csg/OpenMCInput.py
csg2csg/OpenMCMaterial.py
csg2csg/OpenMCSurface.py
csg2csg/ParticleNames.py
csg2csg/PhitsInput.py
csg2csg/SerpentCellCard.py
csg2csg/SerpentInput.py
csg2csg/SerpentMaterialCard.py
csg2csg/SerpentSurfaceCard.py
csg2csg/SurfaceCard.py
csg2csg/Vector.py
csg2csg/__init__.py
csg2csg/csg2csg
csg2csg.egg-info/PKG-INFO
csg2csg.egg-info/SOURCES.txt
csg2csg.egg-info/dependency_links.txt
csg2csg.egg-info/requires.txt
csg2csg.egg-info/top_level.txt