Metadata-Version: 2.1
Name: csg2csg
Version: 0.0.28
Summary: Convert CSG geometry into different formats
Home-page: https://github.com/makeclean/csg2csg
Author: andrew davis
Author-email: andrew.davis@ukaea.uk
License: UNKNOWN
Platform: UNKNOWN
Classifier: Programming Language :: Python :: 3
Classifier: Operating System :: OS Independent
